{
  "rawData": {
    "184": [
      12,
      34
    ]
  },
  "data": [
    {
      "id": 184,
      "name": "group_g1_19",
      "data": 184,
      "type": "number",
      "tableProcessGUId": "67b2e51a-241c-4844-bad3-318e01f7e8f0",
      "producerNodeId": null,
      "producerPort": null,
      "producerArtifactKind": null,
      "provenance": "",
      "processes": []
    }
  ],
  "plots": [
    {
      "id": 36,
      "name": "Stored Value Group result",
      "x": 350,
      "y": 150,
      "width": 500,
      "height": 250,
      "type": "tableplot",
      "selected": false,
      "plot": {
        "columnRefs": [
          184
        ],
        "showCol": [
          true
        ],
        "colCurrent": 1,
        "showColNumber": false,
        "decimalPlaces": 2
      }
    }
  ],
  "tableProcesses": [
    {
      "id": 19,
      "name": "StoredValueGroup",
      "displayName": "Stored Value Group",
      "args": {
        "groups": [
          {
            "id": "g1",
            "name": "GroupA",
            "keys": [
              "demoSV1",
              "demoSV2"
            ]
          }
        ],
        "out": {
          "group_g1": 184
        }
      },
      "refTPId": null
    }
  ],
  "storedValues": {
    "demoSV1": {
      "source": "manual",
      "staticValue": 12
    },
    "demoSV2": {
      "source": "manual",
      "staticValue": 34
    }
  },
  "nodeNotes": {},
  "notes": [],
  "groups": [],
  "orphanProcesses": [],
  "appState": {
    "currentTab": "null",
    "currentControlTab": "properties",
    "loadingState": {
      "isLoading": true,
      "loadingMsg": "Warming up..."
    },
    "showNavbar": true,
    "showDisplayPanel": false,
    "showControlPanel": false,
    "windowWidth": 1024,
    "windowHeight": 768,
    "widthNavBar": 56,
    "widthDisplayPanel": 250,
    "widthControlPanel": 250,
    "gridSize": 15,
    "canvasOffset": {
      "x": 0,
      "y": 0
    },
    "canvasScale": 1,
    "view": "canvas",
    "displayTimezone": "utc",
    "invisiblePlotIds": [],
    "canvasSelectedNodeId": null,
    "canvasMultiSelectedCount": 0,
    "canvasMultiSelectedNodeIds": [],
    "appColours": [
      "#234154",
      "#BE796B",
      "#3E7295",
      "#EDADAD",
      "#A6ACD5",
      "#83422A",
      "#6B9FD5",
      "#4A1E0E",
      "#fbe67280"
    ],
    "showColourPicker": false,
    "showAYSModal": false,
    "AYStext": "",
    "AYScallback": null,
    "AYSoptions": [
      "Yes",
      "No"
    ],
    "showWorkflow": false
  },
  "version": "β.43.2"
}